<?xml version="1.0" encoding="utf-8"?>
<!-- This XML was generated by Rcomage v1.1.1 -->
<TextLang>
	<Text name="msg_setting">Inställningar</Text>
	<Text name="msg_photo">Foto</Text>
	<Text name="msg_music">Musik</Text>
	<Text name="msg_video">Video</Text>
	<Text name="msg_game">Spel</Text>
	<Text name="msg_net">Nätverk</Text>
	<Text name="msg_friend">Vänner</Text>
	<Text name="msg_user">Användare</Text>
	<Text name="msg_login">Logga in</Text>
	<Text name="msg_tv">TV</Text>
	<Text name="msg_psn">PlayStation®
Network</Text>
	<Text name="msg_power_off_console2">Stäng av systemet</Text>
	<Text name="msg_photo_gallery">Photo Gallery</Text>
	<Text name="msg_untitled">Okänd</Text>
	<Text name="msg_new_vmc">Skapa nytt internt Memory Card</Text>
	<Text name="msg_signup">Registrera dig för PlayStation®Network</Text>
	<Text name="msg_playstation_home">PlayStation®Home</Text>
	<Text name="msg_start_new_chat2">Starta en ny chatt</Text>
	<Text name="msg_ms">Memory Stick™</Text>
	<Text name="msg_sd">SD Memory Card</Text>
	<Text name="msg_cf">CompactFlash®</Text>
	<Text name="msg_bd_rom">BD-ROM</Text>
	<Text name="msg_bd_r">BD-R</Text>
	<Text name="msg_bd_re">BD-RE</Text>
	<Text name="msg_dvdr">DVD-R</Text>
	<Text name="msg_dvdplusr">DVD+R</Text>
	<Text name="msg_dvdrw">DVD-RW</Text>
	<Text name="msg_dvdplusrw">DVD+RW</Text>
	<Text name="msg_dvdrom">DVD-ROM</Text>
	<Text name="msg_dvdvideo">DVD Video</Text>
	<Text name="msg_dvdvr">DVD-VR</Text>
	<Text name="msg_dvdplusvr">DVD+VR</Text>
	<Text name="msg_avchd">AVCHD</Text>
	<Text name="msg_avcrec">AVCREC</Text>
	<Text name="msg_bdmv">BDMV</Text>
	<Text name="msg_bdav">BDAV</Text>
	<Text name="msg_cdaudio">Ljud-CD</Text>
	<Text name="msg_cddata">Dataskiva</Text>
	<Text name="msg_sacd">Super Audio CD</Text>
	<Text name="msg_mc_ps1">Memory Card (PS)</Text>
	<Text name="msg_mc_ps2">Memory Card (PS2)</Text>
	<Text name="msg_disc">Skiva</Text>
	<Text name="msg_dsd_disc">DSD-skiva</Text>
	<Text name="msg_psp">PSP™ (PlayStation®Portable)</Text>
	<Text name="msg_psp_bracket">PSP™ (PlayStation®Portable) %1</Text>
	<Text name="msg_psp_name">Smeknamn</Text>
	<Text name="msg_usb">USB-enhet</Text>
	<Text name="msg_usb_id">USB-enhet (%1)</Text>
	<Text name="msg_digitalcamera">Digitalkamera</Text>
	<Text name="msg_digitalcamera_id">Digitalkamera (%1)</Text>
	<Text name="msg_walkman">ATRAC Audio Device</Text>
	<Text name="msg_walkman_id">ATRAC Audio Device (%1)</Text>
	<Text name="msg_cancel">Avbryt</Text>
	<Text name="msg_ok">OK</Text>
	<Text name="msg_fix">OK</Text>
	<Text name="msg_yes">Ja</Text>
	<Text name="msg_no">Nej</Text>
	<Text name="msg_on">På</Text>
	<Text name="msg_off">Av</Text>
	<Text name="msg_nrml">Normal</Text>
	<Text name="msg_normal">Normal</Text>
	<Text name="msg_plus1">+1</Text>
	<Text name="msg_plus2">+2</Text>
	<Text name="msg_plus3">+3</Text>
	<Text name="msg_plus4">+4</Text>
	<Text name="msg_minus1">-1</Text>
	<Text name="msg_minus2">-2</Text>
	<Text name="msg_minus3">-3</Text>
	<Text name="msg_minus4">-4</Text>
	<Text name="msg_1">1</Text>
	<Text name="msg_2">2</Text>
	<Text name="msg_3">3</Text>
	<Text name="msg_4">4</Text>
	<Text name="msg_5">5</Text>
	<Text name="msg_percent">%1%%</Text>
	<Text name="msg_image_count_value">%1 bild</Text>
	<Text name="msg_images_count_value">%1 bilder</Text>
	<Text name="msg_track_count_value">%1 Spår</Text>
	<Text name="msg_tracks_count_value">%1 Spår</Text>
	<Text name="msg_title_count_value">%1 Titel</Text>
	<Text name="msg_titles_count_value">%1 Titlar</Text>
	<Text name="msg_savedata_count_value">%1 Spara</Text>
	<Text name="msg_savedatas_count_value">%1 Sparar</Text>
	<Text name="msg_time_num1">%1:%2:%3</Text>
	<Text name="msg_time_num2">%1:%2'%3''</Text>
	<Text name="msg_time_num3">%1'%2''</Text>
	<Text name="msg_datetime_num1">%1/%2/%3  %4:%5</Text>
	<Text name="msg_am">AM</Text>
	<Text name="msg_pm">PM</Text>
	<Text name="msg_time_hour_num2">%1:%2'</Text>
	<Text name="msg_day_plural">%1 dagar</Text>
	<Text name="msg_sort">Sortera efter</Text>
	<Text name="msg_importeddate_f">Importdatum ▲</Text>
	<Text name="msg_importeddate_r">Importdatum ▼</Text>
	<Text name="msg_shootdate_f">Filmdatum ▲</Text>
	<Text name="msg_shootdate_r">Filmdatum ▼</Text>
	<Text name="msg_sale_year_f">Utgivningsår ▲</Text>
	<Text name="msg_sale_year_r">Utgivningsår ▼</Text>
	<Text name="msg_created_date_time_f">Skapad den ▲</Text>
	<Text name="msg_created_date_time_r">Skapad den ▼</Text>
	<Text name="msg_updated_date_f">Uppdaterad den ▲</Text>
	<Text name="msg_updated_date_r">Uppdaterad den ▼</Text>
	<Text name="msg_format_f">Format</Text>
	<Text name="msg_imagename_f">Bildnamn</Text>
	<Text name="msg_albumname_f">Albumnamn</Text>
	<Text name="msg_genre_f">Genrenamn</Text>
	<Text name="msg_artist_f">Artistnamn</Text>
	<Text name="msg_track_f">Spårnamn</Text>
	<Text name="msg_title_f">Titelnamn</Text>
	<Text name="msg_subtitle_f">Undertitel</Text>
	<Text name="msg_start_date_f">Nyligen spelade</Text>
	<Text name="msg_folder_class">Gruppera innehåll</Text>
	<Text name="msg_all">Alla</Text>
	<Text name="msg_year_folder">Efter årtal</Text>
	<Text name="msg_month_folder">Efter månad</Text>
	<Text name="msg_album_folder">Efter album</Text>
	<Text name="msg_genre_folder">Efter genre</Text>
	<Text name="msg_artist_folder">Efter artist</Text>
	<Text name="msg_sale_year_folder">Efter utgivningsår</Text>
	<Text name="msg_track_folder">Efter spår</Text>
	<Text name="msg_title_folder">Efter titel</Text>
	<Text name="msg_format_folder">Efter format</Text>
	<Text name="msg_copy">Kopiera</Text>
	<Text name="msg_copy_plural">Kopiera flera</Text>
	<Text name="msg_del">Radera</Text>
	<Text name="msg_del_plural">Radera flera</Text>
	<Text name="msg_slideshow">Bildspel</Text>
	<Text name="msg_display_all">Visa alla</Text>
	<Text name="msg_cddbdata_get">Hämta CD-information</Text>
	<Text name="msg_import">Importera</Text>
	<Text name="msg_titlelist">Titellista</Text>
	<Text name="msg_play">Spela upp</Text>
	<Text name="msg_play_begin">Spela upp från början</Text>
	<Text name="msg_smove">Flytta</Text>
	<Text name="msg_disc_eject">Mata ut skivan</Text>
	<Text name="msg_info">Information</Text>
	<Text name="msg_repeat">Upprepa</Text>
	<Text name="msg_shuffle">Blanda</Text>
	<Text name="msg_pause">Paus</Text>
	<Text name="msg_display">Visa</Text>
	<Text name="msg_volume_control">Volymkontroll</Text>
	<Text name="msg_plus">+</Text>
	<Text name="msg_minus">-</Text>
	<Text name="msg_slideshow_with_icon">Bildspel </Text>
	<Text name="msg_fix_with_icon">OK </Text>
	<Text name="msg_folder_class_with_icon">Gruppera innehåll </Text>
	<Text name="msg_option_with_icon">: Alternativ</Text>
	<Text name="msg_help_start">: Starta</Text>
	<Text name="msg_icon_start"></Text>
	<Text name="msg_info_none">-</Text>
	<Text name="msg_format">Format</Text>
	<Text name="msg_size">Storlek</Text>
	<Text name="msg_space">Ledigt utrymme</Text>
	<Text name="msg_shoot_date">Filmat</Text>
	<Text name="msg_updated_date">Uppdaterat</Text>
	<Text name="msg_corrupted_data">Skadade data</Text>
	<Text name="msg_unsupported_data">Data som inte stöds</Text>
	<Text name="msg_folder">Mapp</Text>
	<Text name="msg_resolution">Upplösning</Text>
	<Text name="msg_multiply">%1 x %2</Text>
	<Text name="msg_image">Bild</Text>
	<Text name="msg_image_count">Bilder</Text>
	<Text name="msg_camera">Filmenhet</Text>
	<Text name="msg_album">Album</Text>
	<Text name="msg_genre">Genre</Text>
	<Text name="msg_artist">Artist</Text>
	<Text name="msg_imported_size">Storlek efter import</Text>
	<Text name="msg_size_counting">Räknar...</Text>
	<Text name="msg_sale_year">Utgivet</Text>
	<Text name="msg_play_time">Längd</Text>
	<Text name="msg_comment">Kommentar</Text>
	<Text name="msg_samplingfrequency">Samplingsfrekvens</Text>
	<Text name="msg_disc_number">Skivnummer</Text>
	<Text name="msg_track_count">Spår</Text>
	<Text name="msg_track_number">Spårnummer</Text>
	<Text name="msg_track">Spår</Text>
	<Text name="msg_bpm">BPM</Text>
	<Text name="msg_codec">Codec</Text>
	<Text name="msg_lastplay_datetime">Senast uppspelad</Text>
	<Text name="msg_ch">Kanal</Text>
	<Text name="msg_various_artists">Blandade artister</Text>
	<Text name="msg_imported_date">Importerat</Text>
	<Text name="msg_created_date">Filmat</Text>
	<Text name="msg_start_date">Börjar</Text>
	<Text name="msg_expiration_date">Utlöper</Text>
	<Text name="msg_remaining_time">Kvarvarande timmar</Text>
	<Text name="msg_play_count">Antal uppspelningar</Text>
	<Text name="msg_file_number">Filnummer</Text>
	<Text name="msg_title">Titel</Text>
	<Text name="msg_subtitle">Undertitel</Text>
	<Text name="msg_disc_type">Typ av skiva</Text>
	<Text name="msg_disc_protect">Lösenordsspärr</Text>
	<Text name="msg_title_count">Titlar</Text>
	<Text name="msg_video_codec">Videocodec</Text>
	<Text name="msg_audio_codec">Ljudcodec</Text>
	<Text name="msg_file_type">Filtyp</Text>
	<Text name="msg_mediaserver">Mediaserver</Text>
	<Text name="msg_dlna_date_time">Datum och tid</Text>
	<Text name="msg_produced_date">Tillverkad</Text>
	<Text name="msg_owner">Ägare</Text>
	<Text name="msg_info_valid_from">Börjar</Text>
	<Text name="msg_info_valid_to">Utlöper</Text>
	<Text name="msg_all_use_content_delete_cannot_use">Detta innehåll kan användas av andra än ägaren till innehållet. Om alla ägare har tagits bort kommer du dock inte att kunna spela upp innehållet.</Text>
	<Text name="msg_need_signin_to_use_content">Du måste vara inloggad som ägare på PlayStation®Network för att spela upp detta innehåll.</Text>
	<Text name="msg_need_save_psn_pw_other_owner_use_content">Detta innehåll kan spelas upp av användare som inte är innehållets ägare. Ägarens PlayStation®Network-lösenord måste dock sparas på systemet för att andra användare ska kunna använda innehållet.</Text>
	<Text name="msg_only_for_psp_need_copy_pls">Detta innehåll ska endast användas tillsammans med PSP™-systemet. Du måste kopiera innehållet till PSP™-systemet för att kunna använda det.</Text>
	<Text name="msg_magicgate">MagicGate™</Text>
	<Text name="msg_mg_supported">Stöds</Text>
	<Text name="msg_mg_not_supported">Stöds inte</Text>
	<Text name="msg_info_unknown">Okänd</Text>
	<Text name="msg_savedata_count">Sparar</Text>
	<Text name="msg_model">Modell</Text>
	<Text name="msg_can_play_only_for_variable_hours">(Obs! Innehållet kan bara spelas upp igen inom %1 timmar efter första uppspelningen.)</Text>
	<Text name="msg_can_play_only_for_variable_hours_game">(Obs! Innehållet kan bara spelas upp igen inom %1 minuter efter första starten.)</Text>
	<Text name="msg_video_description">Beskrivning</Text>
	<Text name="msg_copyright">Copyright-information</Text>
	<Text name="msg_jpeg">JPEG</Text>
	<Text name="msg_gif">GIF</Text>
	<Text name="msg_png">PNG</Text>
	<Text name="msg_tiff">TIFF</Text>
	<Text name="msg_bmp">BMP</Text>
	<Text name="msg_aac_kbps">AAC %1 kbps</Text>
	<Text name="msg_mp3_kpbs">MP3 %1 kbps</Text>
	<Text name="msg_atrac_kbps">ATRAC %1 kbps</Text>
	<Text name="msg_wma_kbps">WMA %1 kbps</Text>
	<Text name="msg_lpcm_bit_ch">Linjär PCM  %1 Bit  %2 kan.</Text>
	<Text name="msg_non_lpcm">Non-linear PCM %1 kbps</Text>
	<Text name="msg_dsd_ch">DSD %1 kan.</Text>
	<Text name="msg_dolby">Dolby Digital</Text>
	<Text name="msg_mpeg1">MPEG-1</Text>
	<Text name="msg_mpeg2">MPEG-2</Text>
	<Text name="msg_mpeg2_ts">MPEG-2 TS</Text>
	<Text name="msg_mpeg4">MPEG-4</Text>
	<Text name="msg_mpeg_layer1">MPEG Layer 1</Text>
	<Text name="msg_mpeg_layer2">MPEG Layer 2</Text>
	<Text name="msg_mpeg_layer3">MPEG Layer 3</Text>
	<Text name="msg_avc">AVC</Text>
	<Text name="msg_motion_jpeg">Motion JPEG</Text>
	<Text name="msg_divx">DivX®</Text>
	<Text name="msg_wmv">VC-1 (WMV)</Text>
	<Text name="msg_mpeg1_mbps">MPEG-1 %1 Mbps</Text>
	<Text name="msg_mpeg2_mbps">MPEG-2 %1 Mbps</Text>
	<Text name="msg_mpeg2_ts_mbps">MPEG-2 TS %1 Mbps</Text>
	<Text name="msg_mpeg4_mbps">MPEG-4 %1 Mbps</Text>
	<Text name="msg_avc_kbps">AVC %1 kbps</Text>
	<Text name="msg_khz">%1 kHz</Text>
	<Text name="msg_kbps">%1 kbps</Text>
	<Text name="msg_mbps">%1 Mbps</Text>
	<Text name="msg_ch_2">2 kan.</Text>
	<Text name="msg_multi_ch">Multi-kanal</Text>
	<Text name="msg_power_off_console">Stäng av systemet</Text>
	<Text name="msg_turnoff_system_ask">Vill du stänga av systemet?</Text>
	<Text name="msg_after_background_download_auto_turn_off">Stäng av systemet automatiskt efter att nedladdningen slutförts i bakgrunden</Text>
	<Text name="msg_slot_assign">Tilldela fack</Text>
	<Text name="msg_slot1">Fack 1</Text>
	<Text name="msg_slot2">Fack 2</Text>
	<Text name="msg_eject">Ta bort</Text>
	<Text name="msg_user_name">Användarnamn</Text>
	<Text name="msg_need_quit_to_operate_ask">För att utföra denna åtgärd måste du stänga [%1].
Vill du stänga programvaran nu?</Text>
	<Text name="msg_error_hdd_full_perform_operation">Det finns inte tillräckligt med ledigt utrymme på hårddisken.
För att utföra denna åtgärd krävs ytterligare minst %1 ledigt utrymme.</Text>
	<Text name="msg_content_already_copied">Detta innehåll har kanske redan kopierats.</Text>
	<Text name="msg_save_newly">Spara ny</Text>
	<Text name="msg_original_content">Existerande innehåll</Text>
	<Text name="msg_new_content">Nytt innehåll</Text>
	<Text name="msg_save_destination_select">Välj destination.</Text>
	<Text name="msg_error_no_storagemedia">Anslut lagringsmediet i spardestinationen.</Text>
	<Text name="msg_ps3_photo">Hårddisk (Foto)</Text>
	<Text name="msg_ps3_video">Hårddisk (Video)</Text>
	<Text name="msg_ps3_music">Hårddisk (Musik)</Text>
	<Text name="msg_folder_name">Mappnamn</Text>
	<Text name="msg_same_name_file">Spardestinationen har en fil med samma namn.</Text>
	<Text name="msg_different_name_save">Ändra namnet och spara</Text>
	<Text name="msg_overwrite_save">Skriv över och spara</Text>
	<Text name="msg_save_no">Spara inte</Text>
	<Text name="msg_save_yes">Spara</Text>
	<Text name="msg_apply_all">Använd för alla</Text>
	<Text name="msg_select_all">Välj alla</Text>
	<Text name="msg_deselect_all">Återställ alla</Text>
	<Text name="msg_copying">Kopiering pågår...
Vänta.</Text>
	<Text name="msg_copied">Kopieringen har slutförts.</Text>
	<Text name="msg_copy_incomplete_ms_ask">Memory Stick™-enhetens lediga utrymme är för litet. Kopieringsåtgärden kanske inte slutförs.
Vill du fortsätta?</Text>
	<Text name="msg_copy_incomplete_sd_ask">SD Memory Card-enhetens lediga utrymme är för litet. Kopieringsåtgärden kanske inte slutförs.
Vill du fortsätta?</Text>
	<Text name="msg_copy_incomplete_cf_ask">CompactFlash®-enhetens lediga utrymme är för litet. Kopieringsåtgärden kanske inte slutförs.
Vill du fortsätta?</Text>
	<Text name="msg_copy_incomplete_usb_ask">USB-enhetens lediga utrymme är för litet. Kopieringsåtgärden kanske inte slutförs.
Vill du fortsätta?</Text>
	<Text name="msg_copy_incomplete_hdd_ask">Hårddiskens lediga utrymme är för litet. Kopieringsåtgärden kanske inte slutförs.
Vill du fortsätta?</Text>
	<Text name="msg_copy_incomplete">Det lediga utrymmet är för litet. Kopieringsåtgärden slutfördes inte.</Text>
	<Text name="msg_completed_count">Slutförd</Text>
	<Text name="msg_copy_cancel_ask">Vill du avbryta kopieringsåtgärden?</Text>
	<Text name="msg_error_content_over_copy">Det högsta antal innehållsobjekt som går att spara har uppnåtts. Kopieringsåtgärden slutfördes inte.</Text>
	<Text name="msg_sure_to_delete_ask">Ska raderingen utföras?</Text>
	<Text name="msg_deleting">Radering pågår...
Vänta.</Text>
	<Text name="msg_deleted">Raderingen har slutförts.</Text>
	<Text name="msg_cannot_delete_folder_on_this_system">Det går inte att radera mappen med detta system.</Text>
	<Text name="msg_change_upfolder">Flytta till mappen ovanför</Text>
	<Text name="msg_create_newfolder">Skapa ny mapp</Text>
	<Text name="msg_folder_name_new">Ny mapp %1</Text>
	<Text name="msg_error_no_folder">Det finns ingen mapp.</Text>
	<Text name="msg_wait">Vänta...</Text>
	<Text name="msg_error">Ett fel har inträffat.</Text>
	<Text name="msg_error_corrupted_data">Det finns skadade data.</Text>
	<Text name="msg_error_unsupported_data">Datatypen stöds inte.</Text>
	<Text name="msg_error_copy">Ett fel inträffade när kopieringsåtgärden utfördes.</Text>
	<Text name="msg_error_del">Ett fel inträffade när raderingsåtgärden utfördes.</Text>
	<Text name="msg_error_no_name">Inget namn har angetts.
Ange ett namn som består av minst 1 tecken.</Text>
	<Text name="msg_error_ms_full">Memory Stick™-enhetens lediga utrymme är för litet.</Text>
	<Text name="msg_error_ms_locked">Memory Stick™-enheten är låst.</Text>
	<Text name="msg_error_ms_no_access">Det går inte att komma åt Memory Stick™-enheten.</Text>
	<Text name="msg_error_ms_no_read">Det går inte att läsa Memory Stick™-enheten.</Text>
	<Text name="msg_error_no_ms">Ingen Memory Stick™-enhet är insatt.</Text>
	<Text name="msg_error_sd_full">SD Memory Card-enhetens lediga utrymme är för litet.</Text>
	<Text name="msg_error_sd_locked">SD Memory Card är låst.</Text>
	<Text name="msg_error_sd_no_access">Det går inte att komma åt SD Memory Card.</Text>
	<Text name="msg_error_sd_no_read">Det går inte att läsa SD Memory Card.</Text>
	<Text name="msg_error_no_sd">Inget SD Memory Card är insatt.</Text>
	<Text name="msg_error_cf_full">CompactFlash®-enhetens lediga utrymme är för litet.</Text>
	<Text name="msg_error_cf_locked">CompactFlash®-enheten är låst.</Text>
	<Text name="msg_error_cf_no_access">Det går inte att komma åt CompactFlash®-enheten.</Text>
	<Text name="msg_error_cf_no_read">Det går inte att läsa CompactFlash®-enheten.</Text>
	<Text name="msg_error_no_cf">Ingen CompactFlash®-enhet är insatt.</Text>
	<Text name="msg_error_usb_full">USB-enhetens lediga utrymme är för litet.</Text>
	<Text name="msg_error_usb_locked">USB-enheten är låst.</Text>
	<Text name="msg_error_usb_no_access">Det går inte att komma åt USB-enheten.</Text>
	<Text name="msg_error_usb_no_read">Det går inte att läsa USB-enheten.</Text>
	<Text name="msg_error_no_usb">Ingen USB-enhet är insatt.</Text>
	<Text name="msg_error_hdd_full">Hårddiskens lediga utrymme är för litet.</Text>
	<Text name="msg_error_hdd_no_access">Det går inte att komma åt hårddisken.</Text>
	<Text name="msg_error_no_signin">Du måste logga in på PlayStation®Network.</Text>
	<Text name="msg_error_no_signup">Du måste registrera dig för PlayStation®Network.</Text>
	<Text name="msg_icon_image_select">Välj en bild som ska användas som ikon.</Text>
	<Text name="msg_icon_change_albumtrack_ask1">Ikonerna ändras för samtliga av albumets spår.
Vill du fortsätta?</Text>
	<Text name="msg_cannot_display_all_mediaserver">Det finns för många mediaservrar.
Några mediaservrar kommer inte att visas.</Text>
	<Text name="msg_scan_mediaserver">Sök mediaservrar</Text>
	<Text name="msg_not_allowed_access_confirm_pls">Åtkomst till mediaservern är förbjuden. Det är möjligt att systemnamnet för detta PS3™ system, "%1", inte har registrerats.
Kontrollera inställningarna för mediaservern.</Text>
	<Text name="msg_playlists">Spellistor</Text>
	<Text name="msg_playlist_pane">Spellista</Text>
	<Text name="msg_create_new_playlist">Skapa ny spellista</Text>
	<Text name="msg_to_add_content_playlist_select_edit">Välj [Redigera] från alternativmenyn för att lägga till innehåll till denna spellista.</Text>
	<Text name="msg_error_cannot_edit_playlist_no_track">Det finns inga spår på hårddisken. Spellistan kan inte redigeras.</Text>
	<Text name="msg_error_cannot_edit_playlist_no_image">Det finns inga bilder på hårddisken. Spellistan kan inte redigeras.</Text>
	<Text name="msg_error_same_name_cannot_use">Detta namn är redan i bruk.
Ange ett annat namn.</Text>
	<Text name="msg_add_to_playlist">Lägg till i spellistan</Text>
	<Text name="msg_add_playlist">Lägg till</Text>
	<Text name="msg_add_all_playlist">Lägg till alla</Text>
	<Text name="msg_delete_playlist_ask">Spellistan kommer att raderas.
Är du säker på att du vill fortsätta?</Text>
	<Text name="msg_error_startdate_video">Innehållet är inte tillgängligt före startdatumet.</Text>
	<Text name="msg_error_expired_video">Innehållet har upphört att gälla och är inte tillgängligt.</Text>
	<Text name="msg_info_no_time_limit">Ingen tidsgräns</Text>
	<Text name="msg_info__expired">Utlöpt</Text>
	<Text name="msg_expires_on_variable">Utlöper %1</Text>
	<Text name="msg_error_timelimited_video"><![CDATA[Detta innehåll har en tidsbegränsning.
För att utföra denna åtgärd, gå till [Inställningar] > [Datum- och tidsinställningar] > [Datum och tid], och välj [Ställ in via Internet] för att ställa in tid och datum.]]></Text>
	<Text name="msg_move_delete_hdd_cannot_move_back_ask">Om du flyttar detta innehåll kommer det att raderas från systemets hårddisk.
Du kommer inte att kunna flytta tillbaka innehållet till detta system.
Är du säker på att du vill fortsätta?</Text>
	<Text name="msg_can_play_variable_first_play_now_ask">Det här innehållet kan bara spelas upp i %1 timmar efter den första uppspelningen.
Vill du spela upp det nu?</Text>
	<Text name="msg_del_content_cannot_dl_again_conf_psn">Innehållet kommer att raderas och kan inte laddas ned på nytt.
Är du säker på att du vill fortsätta?</Text>
	<Text name="msg_download_psstore_turn_on_off_everyday">Rekommenderat innehåll från PlayStation®Store laddas ner automatiskt.
PS3™-systemet startar automatiskt varje dag för att söka efter rekommenderat innehåll. När åtgärden är slutförd, stänger systemet automatiskt av sig.</Text>
	<Text name="msg_to_download_psstore_auto_login_signin">För att automatiskt ladda ner rekommenderat innehåll från PlayStation®Store måste du vara inställd på automatisk inloggning i [Användare] och automatisk inloggning för  PlayStation®Network. Läs i online bruksanvisningarna för instruktioner om hur man gör dessa inställningar.</Text>
	<Text name="msg_to_enable_setting_enable_auto_login">Ändringarna du gjort har avaktiverat följande inställningar.
%1

För att aktivera dessa inställningar måste du ställa in en användare på automatisk inloggning under [Användare]. För information om hur man ställer in den automatiska inloggningen hänvisas till online-handboken.</Text>
	<Text name="msg_to_enable_setting_enable_auto_signin">Ändringarna du gjort har avaktiverat följande inställningar.
%1

För att aktivera dessa inställningar måste du ställa in på automatisk inloggning till PlayStation®Network. För information om hur man ställer in på automatisk inloggning hänvisas till online-handboken.</Text>
	<Text name="msg_remoteplay_remote_start"><![CDATA[[Inställningar] > [Inställningar för fjärrspel] > [Fjärrstart]]]></Text>
	<Text name="msg_console_setting_auto_download"><![CDATA[[Inställningar] > [Systeminställningar] > [Automatisk nedladdning]]]></Text>
	<Text name="msg_lang_japan">Japanska</Text>
	<Text name="msg_lang_english">Engelska</Text>
	<Text name="msg_lang_french">Franska</Text>
	<Text name="msg_lang_spanish">Spanska</Text>
	<Text name="msg_lang_german">Tyska</Text>
	<Text name="msg_lang_italian">Italienska</Text>
	<Text name="msg_lang_dutch">Holländska</Text>
	<Text name="msg_lang_portuguese">Portugisiska</Text>
	<Text name="msg_lang_russian">Ryska</Text>
	<Text name="msg_lang_polish">Polska</Text>
	<Text name="msg_lang_finnish">Finska</Text>
	<Text name="msg_lang_danish">Danska</Text>
	<Text name="msg_lang_norwegian">Norska</Text>
	<Text name="msg_lang_swedish">Svenska</Text>
	<Text name="msg_lang_korean">Koreanska</Text>
	<Text name="msg_lang_chinese_t">Traditionell kinesiska</Text>
	<Text name="msg_lang_chinese_s">Förenklad kinesiska</Text>
	<Text name="msg_lpcm">Linjär PCM</Text>
	<Text name="msg_display_on">Visa</Text>
	<Text name="msg_display_off">Visa inte</Text>
	<Text name="msg_macaddress">MAC-adress</Text>
	<Text name="msg_ipaddress">IP-adress</Text>
	<Text name="msg_atrac_not_activated_set_pls"><![CDATA[ATRAC är inte aktiverat.
Gå till [Inställningar] > [Systeminställningar] och aktivera ATRAC.]]></Text>
	<Text name="msg_backup">Säkerhetskopiera</Text>
	<Text name="msg_restore">Återställ</Text>
	<Text name="msg_audio_device_setting">Inställningar för ljudenhet</Text>
	<Text name="msg_print">Skriv ut</Text>
	<Text name="msg_manufacturer">Tillverkare</Text>
	<Text name="msg_10min">Efter 10 minuter</Text>
	<Text name="msg_20min">Efter 20 minuter</Text>
	<Text name="msg_30min">Efter 30 minuter</Text>
	<Text name="msg_remain_time">Återstående tid</Text>
	<Text name="msg_others">Övriga</Text>
	<Text name="msg_level_1">Nivå 1</Text>
	<Text name="msg_level_2">Nivå 2</Text>
	<Text name="msg_level_3">Nivå 3</Text>
	<Text name="msg_level_4">Nivå 4</Text>
	<Text name="msg_level_5">Nivå 5</Text>
	<Text name="msg_level_6">Nivå 6</Text>
	<Text name="msg_level_7">Nivå 7</Text>
	<Text name="msg_level_8">Nivå 8</Text>
	<Text name="msg_level_9">Nivå 9</Text>
	<Text name="msg_level_10">Nivå 10</Text>
	<Text name="msg_level_11">Nivå 11</Text>
	<Text name="msg_gameetc_pc">Föräldrakontroll</Text>
	<Text name="msg_netservice">PlayStation®Network</Text>
	<Text name="msg_error_server_connect_timeout">Anslutningen till servern överskred tidsgränsen.</Text>
	<Text name="msg_cannot_operate_in_demonstration_mode">Det går inte att utföra den här åtgärden i demoläget.</Text>
	<Text name="msg_tool_app_home_ps3_game"><![CDATA[★ /app_home/PS3_GAME/]]></Text>
	<Text name="msg_tool_title_store_preview">Title Store Preview</Text>
	<Text name="msg_tool_title_store_preview_ingame"><![CDATA[★ Title Store Preview (inGame)]]></Text>
	<Text name="msg_tool_title_store_preview_store"><![CDATA[★ Title Store Preview (Store)]]></Text>
	<Text name="msg_tool_lock"><![CDATA[★ Lock]]></Text>
	<Text name="msg_tool_unlock"><![CDATA[★ Unlock]]></Text>
	<Text name="msg_tool_check"><![CDATA[★ Check]]></Text>
	<Text name="msg_tool_cancel_purchase"><![CDATA[★ Cancel Purchase]]></Text>
	<Text name="msg_tool_del"><![CDATA[★ Delete]]></Text>
	<Text name="msg_tool_import"><![CDATA[★ Import]]></Text>
	<Text name="msg_tool_export"><![CDATA[★ Export]]></Text>
	<Text name="msg_tool_quick_sign_up"><![CDATA[★ Quick Sign Up]]></Text>
	<Text name="msg_tool_performance_bar"><![CDATA[★ Performance Bar]]></Text>
	<Text name="msg_tool_no_memory_limit"><![CDATA[★ No Memory Limit]]></Text>
	<Text name="msg_tool_quick_preview"><![CDATA[★ Quick Preview]]></Text>
	<Text name="msg_tool_owner_info"><![CDATA[★ Owner Information]]></Text>
	<Text name="msg_no_trophy">There are no trophies.</Text>
	<Text name="msg_digitalcamera_image">Digitalkamerabilder</Text>
	<Text name="msg_del_image_ask">Bilden raderas.
Vill du fortsätta?</Text>
	<Text name="msg_del_images_ask">De valda bilderna raderas.
Vill du fortsätta?</Text>
	<Text name="msg_del_camerafolder_ask">Mappen och alla bilder i den, även skyddade bilder, raderas.
Vill du fortsätta?</Text>
	<Text name="msg_del_image_protected_ask">Den här bilden är skyddad.
Ska den raderas?</Text>
	<Text name="msg_del_imagefolder_ask">Mappen och alla bilder i den raderas.
Vill du fortsätta?</Text>
	<Text name="msg_error_del_imagefolder">Raderingen misslyckades.
Mappen innehåller information som inte är bilddata.</Text>
	<Text name="msg_del_image_select">Välj bilder som ska raderas.</Text>
	<Text name="msg_copy_image_select">Välj bilder som ska kopieras.</Text>
	<Text name="msg_copy_image_hdd_ask">Bilden kopieras till hårddisken.</Text>
	<Text name="msg_copy_imagefolder_ask">Alla bilder i mappen kopieras till hårddisken.</Text>
	<Text name="msg_error_no_image_copy">Det finns inga bilder som går att kopiera.</Text>
	<Text name="msg_error_no_image">Det finns inga bilder.</Text>
	<Text name="msg_mmyyyy_jan">Jan %1</Text>
	<Text name="msg_mmyyyy_feb">Feb %1</Text>
	<Text name="msg_mmyyyy_mar">Mar %1</Text>
	<Text name="msg_mmyyyy_apr">Apr %1</Text>
	<Text name="msg_mmyyyy_may">Maj %1</Text>
	<Text name="msg_mmyyyy_jun">Jun %1</Text>
	<Text name="msg_mmyyyy_jul">Jul %1</Text>
	<Text name="msg_mmyyyy_aug">Aug %1</Text>
	<Text name="msg_mmyyyy_sep">Sep %1</Text>
	<Text name="msg_mmyyyy_oct">Okt %1</Text>
	<Text name="msg_mmyyyy_nov">Nov %1</Text>
	<Text name="msg_mmyyyy_dec">Dec %1</Text>
	<Text name="msg_yyyy">%1</Text>
	<Text name="msg_slideshow_type1">Dia</Text>
	<Text name="msg_slideshow_type2">Porträtt</Text>
	<Text name="msg_slideshow_type3">Fotoalbum</Text>
	<Text name="msg_slideshow_type4">Fotoalbum 2</Text>
	<Text name="msg_piccto_explanation">Skapa en plats där du kan njuta av och förbättra dina foton.
Förvandla fotona på ditt PS3™-system till snygga album på några minuter.
Du kan sortera dina foton tematiskt, lägga till musik för att förbättra ett bildspel eller lägga till anpassade ramar på fotona. Ju fler foton du lägger till desto roligare kan du ha - möjligheterna är oändliga!</Text>
	<Text name="msg_piccto_explanation_sd">Skapa en plats där du kan njuta av och förbättra dina foton.
Förvandla fotona på ditt PS3™-system till snygga album på några minuter.</Text>
	<Text name="msg_cddbdata_getting">CD-information hämtas...
Vänta.</Text>
	<Text name="msg_cddbdata_pluralfound_select">Flera CD-informationsposter hittades.
Välj en CD-informationspost.</Text>
	<Text name="msg_cddbdata_send">Skicka CD-information</Text>
	<Text name="msg_cddbdata_sending">CD-information skickas...
Vänta.</Text>
	<Text name="msg_copy_track_select">Välj spår som ska kopieras.</Text>
	<Text name="msg_copy_track_hdd">Spåren kopieras till hårddisken.</Text>
	<Text name="msg_copy_trackfolder">Alla spår i mappen kopieras till hårddisken.</Text>
	<Text name="msg_copy_trackfolder_protect">Alla spår i mappen kopieras till hårddisken.
Skyddade spår kopieras inte.</Text>
	<Text name="msg_import_hdd_incomplete_ask">Hårddiskens lediga utrymme är för litet. Importåtgärden kanske inte slutförs.
Vill du fortsätta?</Text>
	<Text name="msg_del_track_protected_ask">Detta spår är skyddat.
Ska spåret raderas?</Text>
	<Text name="msg_del_folder_track_protected_ask">Mappen och alla spår i den, även skyddade spår, raderas.
Vill du fortsätta?</Text>
	<Text name="msg_del_track_select">Välj spår som ska raderas.</Text>
	<Text name="msg_del_track_ask">Ska spåret raderas?</Text>
	<Text name="msg_del_tracks_ask">Ska de valda spåren raderas?</Text>
	<Text name="msg_del_trackfolder_ask">Mappen och alla spår i den raderas.
Vill du fortsätta?</Text>
	<Text name="msg_error_del_trackfolder_different">Det gick inte att radera mappen.
Mappen innehåller data som inte är musikdata.</Text>
	<Text name="msg_import_track_hdd">Spåren importeras till hårddisken.</Text>
	<Text name="msg_importing">Import pågår...
Vänta.</Text>
	<Text name="msg_import_cancel_ask">Vill du avbryta importåtgärden?</Text>
	<Text name="msg_imported">Importen har slutförts.</Text>
	<Text name="msg_error_import">Ett fel inträffade när importåtgärden utfördes.</Text>
	<Text name="msg_error_track_over">Det högsta antal spår som går att spara har uppnåtts.
Importåtgärden stoppades.</Text>
	<Text name="msg_error_no_trackfolder_copy">Det finns inga spår som går att kopiera.</Text>
	<Text name="msg_error_copyright_track">Copyright-informationen är ogiltig.</Text>
	<Text name="msg_changedinfo_save_music_ask">Vill du spara den ändrade informationen?
Det ändrade innehållet används för alla spår i mappen.</Text>
	<Text name="msg_error_no_track">Det finns inga spår.</Text>
	<Text name="msg_error_no_nexttrack">Inget spår är tillgängligt.</Text>
	<Text name="msg_error_no_prevtrack">Inget spår är tillgängligt.</Text>
	<Text name="msg_track_number_value">Spår %1</Text>
	<Text name="msg_cannot_copy_protected_truck">Copyright-skyddade spår kopieras inte.</Text>
	<Text name="msg_copied_except_copyright_protected_track">Kopieringen har slutförts.
Copyright-skyddade spår kopierades inte.</Text>
	<Text name="msg_select_import">Importera flera</Text>
	<Text name="msg_select_import_pls">Välj spår som ska importeras.</Text>
	<Text name="msg_digitalcamera_video">Digitalkamerafilmer</Text>
	<Text name="msg_psstore_video_offline_explanation_sd">PlayStation®Store är det bästa stället att hyra eller köpa de senaste filmerna för ditt PS3™- eller PSP™-system.
Besök PlayStation®Store idag.</Text>
	<Text name="msg_psstore_video_offline_explanation_hd">PlayStation®Store är det bästa stället att hyra eller köpa de senaste filmerna för ditt PS3™- eller PSP™-system.

Besök PlayStation®Store idag.</Text>
	<Text name="msg_error_no_title">Det finns inga titlar.</Text>
	<Text name="msg_copy_titlefolder">Alla titlar i mappen kopieras till hårddisken.
Copyright-skyddade titlar kopieras inte.</Text>
	<Text name="msg_error_title_over">Det högsta antalet titlar som går att spara har uppnåtts.</Text>
	<Text name="msg_copy_title_hdd_ask">Titlarna kopieras till hårddisken.</Text>
	<Text name="msg_copy_title_select">Välj de titlar som ska kopieras.</Text>
	<Text name="msg_copy_titlefolder2">Copyright-skyddade titlar kopieras inte.</Text>
	<Text name="msg_error_no_title_copy">Det finns inga titlar som går att kopiera.</Text>
	<Text name="msg_error_magicgate_device_required">Det krävs en USB-enhet som är kompatibel med copyright-skyddsfunktionerna, om det ska gå att utföra åtgärden.</Text>
	<Text name="msg_copied_except_copyright_protected_title">Kopieringen har slutförts.
Copyright-skyddade titlar kopierades inte.</Text>
	<Text name="msg_title_number_value">Titel %1</Text>
	<Text name="msg_smove_title_hdd">Titeln flyttas till hårddisken.</Text>
	<Text name="msg_smove_destination_select">Välj en destination.</Text>
	<Text name="msg_smoving">Flyttning pågår...
Vänta.</Text>
	<Text name="msg_smove_cancel_ask">Vill du avbryta flyttåtgärden?</Text>
	<Text name="msg_smoved">Flyttningen har slutförts.</Text>
	<Text name="msg_error_smove">Ett fel inträffade när flyttåtgärden utfördes.</Text>
	<Text name="msg_error_move_mspro">Det går inte att slutföra flyttåtgärden.
Memory Stick PRO™ måste användas om du vill flytta den här titeln.</Text>
	<Text name="msg_del_title_select">Välj den titel som ska raderas.</Text>
	<Text name="msg_del_title_ask">Titeln raderas.
Vill du fortsätta?</Text>
	<Text name="msg_del_titles_ask">De valda titlarna raderas.
Vill du fortsätta?</Text>
	<Text name="msg_del_titlefolder_ask">Mappen och alla titlar i den raderas.
Vill du fortsätta?</Text>
	<Text name="msg_del_camerafolder_video_ask">Mappen och alla titlar i den, även skyddade titlar, raderas.
Vill du fortsätta?</Text>
	<Text name="msg_del_title_protected_ask">Den här titeln är skyddad.
Ska den raderas?</Text>
	<Text name="msg_error_del_movie_folder">Det gick inte att radera mappen.
Mappen innehåller data som inte är videodata.</Text>
	<Text name="msg_error_smove_prohibit">Det går inte att flytta den här titeln.</Text>
	<Text name="msg_corrupted_copyright">Copyright-informationen återställs eftersom den är skadad.</Text>
	<Text name="msg_error_corrupted_copyright">Ett fel inträffade när copyright-informationen återställdes.</Text>
	<Text name="msg_error_no_execute">Den här åtgärden är inte tillgänglig här.</Text>
	<Text name="msg_video_editor_and_upload"><![CDATA[Videoredigering & uppladdning]]></Text>
	<Text name="msg_video_editor_explanation">Du kan redigera en video som du gillar, ladda upp den till en webbplats för videodelning, och sedan inbjuda dina vänner att titta på videon.</Text>
	<Text name="msg_create_new_video">Skapa en ny video</Text>
	<Text name="msg_del_content_ask">Innehållet kommer att raderas.
Är du säker på att du vill fortsätta?</Text>
	<Text name="msg_error_create_content_number_over">Det högsta antalet innehållsobjekt som kan skapas har nåtts.</Text>
	<Text name="msg_backup_data_utility">Verktyg för säkerhetskopiering</Text>
	<Text name="msg_bd_data_utility">Verktyg för BD-data</Text>
	<Text name="msg_common_cache_data">Delad cache data</Text>
	<Text name="msg_bd_data_delete_ask">BD-datan kommer att raderas.
Vill du fortsätta?</Text>
	<Text name="msg_gamedata_utility">Verktyg för speldata</Text>
	<Text name="msg_mc_utility">Verktyg för Memory Card (PS/PS2)</Text>
	<Text name="msg_savedata_utility_minis">Verktyg för sparade data (minis)</Text>
	<Text name="msg_savedata_utility_ps3">Verktyg för sparade data (PS3™)</Text>
	<Text name="msg_content_pc">Föräldrakontrollbegränsat innehåll</Text>
	<Text name="msg_ps1_gamedisc">PlayStation®-skiva</Text>
	<Text name="msg_ps2_gamedisc">PlayStation®2-skiva</Text>
	<Text name="msg_ps2_format_software">PlayStation®2-programvara</Text>
	<Text name="msg_playstation">PlayStation®</Text>
	<Text name="msg_playstation2">PlayStation®2</Text>
	<Text name="msg_playstation3">PlayStation®3</Text>
	<Text name="msg_minis">minis</Text>
	<Text name="msg_pc_engine">PCEngine</Text>
	<Text name="msg_neogeo">NEOGEO</Text>
	<Text name="msg_cannot_start_unless_install_install_ask">Det går bara att starta det här spelet om det installeras på hårddisken.
Vill du börja installera?</Text>
	<Text name="msg_psstore_game_offline_explanation_sd">PlayStation®Store är fulladdad med exklusiva nedladdningsbara spel, GRATIS PS3™-demos, tilläggspaket och videor.

Besök butiken idag!</Text>
	<Text name="msg_psstore_game_offline_explanation_hd">Du kommer åt PlayStation®Store GRATIS* och är det enda stället där du kan ladda ner nya och exklusiva spel, gratis* speldemos, tilläggspaket och videor i HD-format.

Få ut mer av din PS3™ och besök PlayStation®Store idag.

* Bredbandsanslutning till Internet krävs.</Text>
	<Text name="msg_error_cannot_play_ps2_format">Denna modell av PS3™-systemet är inte kompatibel med PlayStation®2-programvara.</Text>
	<Text name="msg_only_for_psp_need_copy_ask">Detta innehåll ska endast användas tillsammans med PSP™-systemet. Du måste kopiera det till ett PSP™-system.
Vill du kopiera det nu?</Text>
	<Text name="msg_error_game_wrong_region">Det går inte att starta den här programvaran på grund av regionsbegränsningar.</Text>
	<Text name="msg_error_gamedisc_cannot_start">Det går inte att starta den här skivan.</Text>
	<Text name="msg_error_game_start_failure">Ett fel inträffade vid startåtgärden.</Text>
	<Text name="msg_current_systemsoftware_update_ask">PS3™-systemets systemprogramvara är av version %1.
Innan det går att starta måste systemprogramvaran uppdateras till version %2 eller senare.
Vill du uppdatera nu?</Text>
	<Text name="msg_systemsoftware_update_ask">Systemprogramvaran måste uppdateras före nästa användning.</Text>
	<Text name="msg_game_start">Starta</Text>
	<Text name="msg_about_game">Om det här spelet</Text>
	<Text name="msg_about_game_ps3_content">Library programs ©Sony Computer Entertainment Inc. Licensed for play on the PlayStation®3 Computer Entertainment System or authorized PlayStation®3 format systems. For full terms and conditions see the user's manual. This product is authorized and produced under license from Sony Computer Entertainment Inc. Use is subject to the copyright laws and the terms and conditions of the user's license.</Text>
	<Text name="msg_game_update_history">Uppdateringshistorik</Text>
	<Text name="msg_purchase">Köp</Text>
	<Text name="msg_installgame_delete_ask">Det installerade spelet raderas.
Vill du fortsätta?</Text>
	<Text name="msg_error_no_savedata">Det finns inga sparade data.</Text>
	<Text name="msg_info_detail">Detaljer</Text>
	<Text name="msg_protection">Lås</Text>
	<Text name="msg_copy_prohibited">Kopiering tillåts inte</Text>
	<Text name="msg_vmc_ps1">Internt Memory Card (PS)</Text>
	<Text name="msg_vmc_ps2">Internt Memory Card (PS2)</Text>
	<Text name="msg_free_space_vmc_ps1">%1 / 120 KB</Text>
	<Text name="msg_free_space_vmc_ps2">%1 / 7998 KB</Text>
	<Text name="msg_error_prohibit_char"><![CDATA[Tecknen "*/:<>?| får inte användas i namn.]]></Text>
	<Text name="msg_category">Typ</Text>
	<Text name="msg_savedata">Sparade data</Text>
	<Text name="msg_savedata_ps1">Sparade data (PlayStation®)</Text>
	<Text name="msg_savedata_ps2">Sparade data (PlayStation®2)</Text>
	<Text name="msg_application_ps2">PlayStation®2-programvara</Text>
	<Text name="msg_application_pocketstation">Programvara (PocketStation™)</Text>
	<Text name="msg_setting_file_ps2">Inställningsfil (PlayStation®2)</Text>
	<Text name="msg_your_bb_navigator">Din PlayStation®BB Navigator</Text>
	<Text name="msg_system_driver_ps1">Systemdrivrutin</Text>
	<Text name="msg_system_driver_ps2">Systemdrivrutin (PlayStation®2)</Text>
	<Text name="msg_system_data">Systemdata</Text>
	<Text name="msg_unknown_data">Okänt</Text>
	<Text name="msg_vmc">Internt Memory Card</Text>
	<Text name="msg_error_no_vmc">Det finns inga interna minneskort.</Text>
	<Text name="msg_free_space_vmc_ps1_w_title">Ledigt utrymme: %1 / 120 KB</Text>
	<Text name="msg_free_space_vmc_ps2_w_title">Ledigt utrymme: %1 / 7998 KB</Text>
	<Text name="msg_pocketstation">PocketStation™</Text>
	<Text name="msg_created_date_time">Skapad</Text>
	<Text name="msg_error_mc_no_access">Det går inte att komma åt minneskortet.</Text>
	<Text name="msg_error_savedata_cannot_copy">Kopiering av den här sparade informationen tillåts inte.</Text>
	<Text name="msg_trophy_collection">Trophysamling</Text>
	<Text name="msg_trophy_count">Trophies</Text>
	<Text name="msg_gain_date">Vunna</Text>
	<Text name="msg_no_trophy_explanation">Det finns inga trophies.
Om du spelar ett spel som har stöd för trophy-funktionen kommer de trophies du vinner att visas här.</Text>
	<Text name="msg_compare_trophy">Jämför trophies</Text>
	<Text name="msg_trophy_grade">Grad</Text>
	<Text name="msg_trophy_platinum">Platina</Text>
	<Text name="msg_trophy_gold">Guld</Text>
	<Text name="msg_trophy_silver">Silver</Text>
	<Text name="msg_trophy_bronze">Brons</Text>
	<Text name="msg_sync_with_server">Synkronisera med server</Text>
	<Text name="msg_trophy_base_addon">Huvudspel/Tillägg</Text>
	<Text name="msg_hidden_trophy_name">Dold trophy</Text>
	<Text name="msg_original_f">Ursprunglig ordning</Text>
	<Text name="msg_trophy_grade_f">Grad</Text>
	<Text name="msg_trophy_earned_f">Datum för vinst ▲</Text>
	<Text name="msg_trophy_earned_r">Datum för vinst ▼</Text>
	<Text name="msg_error_no_gamedata">Det finns inga speldata.</Text>
	<Text name="msg_update_quit_software_update">Den senaste uppdateringsinformationen hittades.
Systemet kommer att avsluta denna programvara och starta installationen.</Text>
	<Text name="msg_playmode">Uppspelningsläge</Text>
	<Text name="msg_no_data">Det finns inga data.</Text>
	<Text name="msg_browser">Webbläsare</Text>
	<Text name="msg_ps3_portal">PlayStation®Store</Text>
	<Text name="msg_psp_connection">Fjärrspel</Text>
	<Text name="msg_remoteplay_explanation"><![CDATA[Använd en enhet som har stöd for fjärrspel (som t.ex. ett PSP™-system) för att fjärranvända det här systemet över nätverk. Gå till [Inställningar] > [Inställningar för fjärrspel] > [Registrera enhet] och registrera fjärrspelsenheten.]]></Text>
	<Text name="msg_onlinemanual">Online bruksanvisningar</Text>
	<Text name="msg_file">Fil</Text>
	<Text name="msg_open">Öppna</Text>
	<Text name="msg_download_cancel_ask">Vill du avbryta nedladdningen?</Text>
	<Text name="msg_internet_search">Internetsök</Text>
	<Text name="msg_error_server_transaction_failure">Ett fel uppstod vid kommunikationen med servern.</Text>
	<Text name="msg_no_file">Det finns inte någon fil.</Text>
	<Text name="msg_content_not_support_remoteplay">Detta innehåll kan inte användas vid fjärrspel.</Text>
	<Text name="msg_error_need_update_psp">Du måste uppdatera programvaran för PSP™-systemet.
Information om olika uppdateringsmetoder finns i anvisningarna till PSP™-systemet.</Text>
	<Text name="msg_error_no_signup_ask">Du måste registrera dig för PlayStation®Network.
Vill du registrera dig nu?</Text>
	<Text name="msg_download_control">Nedladdningshantering</Text>
	<Text name="msg_no_download_content">Det finns inte något att ladda ned.</Text>
	<Text name="msg_variable_downloading">%1%% Laddar ned...</Text>
	<Text name="msg_variable_download_error">%1%% Nedladdningsfel</Text>
	<Text name="msg_variable_download_waiting">%1%% Väntar på nedladdning</Text>
	<Text name="msg_variable_download_pausing">%1%% Paus</Text>
	<Text name="msg_pause_all">Pausa alla</Text>
	<Text name="msg_resume_all">Återuppta alla</Text>
	<Text name="msg_progress">Status</Text>
	<Text name="msg_resume">Återuppta</Text>
	<Text name="msg_download_restart">Återuppta nedladdning</Text>
	<Text name="msg_download_cancel">Avbryt nedladdningen</Text>
	<Text name="msg_install">Installera</Text>
	<Text name="msg_download_content_was_deleted">Innehållet raderades från servern.</Text>
	<Text name="msg_information_board">Information Board</Text>
	<Text name="msg_operate_information_board">Använd</Text>
	<Text name="msg_need_app_software_download_ask">För att använda denna funktion måste du först ladda ner programvaran.
Vill du ladda ner den nu?</Text>
	<Text name="msg_cellbrowser_foldingathome">Folding@home™</Text>
	<Text name="msg_auto_start">Automatisk start</Text>
	<Text name="msg_title_lwp">Life with PlayStation®</Text>
	<Text name="msg_psstore_explanation_sd">PlayStation®Store är fulladdad med exklusiva nedladdningsbara spel, GRATIS PS3™-demos, tilläggspaket och videor.

Besök butiken idag!</Text>
	<Text name="msg_psstore_explanation_hd">Du kommer åt PlayStation®Store GRATIS* och är det enda stället där du kan ladda ner nya och exklusiva spel, gratis* speldemos, tilläggspaket och videor i HD-format.

Få ut mer av din PS3™ och besök PlayStation®Store idag.

* Bredbandsanslutning till Internet krävs.</Text>
	<Text name="msg_reg_explanation_sd">Ta del av GRATIS* onlinespel, nedladdade spel, expansionspaket och exklusivt innehåll, chatta med vänner och jämför troféer.
Bli medlem nu och låt det roliga börja!
* Bredbandsanslutning till Internet krävs.</Text>
	<Text name="msg_reg_explanation_hd">PlayStation®Network handlar uteslutande om underhållning och interaktion.
Ta del av GRATIS* onlinespel, ladda ned fantastiska nya spel, få expansionspaket till en mängd stora titlar, titta på trailers och kom över exklusivt innehåll, chatta med vänner och jämför troféer.

Registrera dig idag – det är enkelt och det är GRATIS!

* Bredbandsanslutning till Internet krävs.</Text>
	<Text name="msg_account_manage">Kontohantering</Text>
	<Text name="msg_can_change_psn_account_psstore_setteing">Justera inställningarna för ditt PlayStation®Network konto eller för inköp från PlayStation®Store.</Text>
	<Text name="msg_your_channel">What's New</Text>
	<Text name="msg_your_channel_offline_explanation_hd">Välkommen till PlayStation®3.
På skärmen "What's New" finns de senaste PlayStation®-nyheterna, uppdateringar och enkel åtkomst till de senaste spelen du spelat.
För att komma till skärmen "What's New", anslut till PlayStation®Network* – det är gratis att gå med och du får tillgång till en hel värld av underhållning, så anmäl dig idag!

* Bredbandsanslutning till Internet krävs.</Text>
	<Text name="msg_your_channel_offline_explanation_sd">På skärmen What's New hittar du de senaste PlayStation®-nyheterna, plus att du får åtkomst till de spel du spelat senast. Anslut till PlayStation®Network* – det är gratis och du får tillgång till en hel värld av underhållning!
* Bredbandsanslutning till Internet krävs.</Text>
	<Text name="msg_your_channel_caution_launching_website">Du lanserar en webbsida.</Text>
	<Text name="msg_psp_exclusive_install_ask">Det här innehållet kan endast användas tillsammans med PSP™-systemet.
Vill du installera det på PSP™-systemet nu?</Text>
	<Text name="msg_bonus_digital_copy">Digital Copy</Text>
	<Text name="msg_bonus_digital_copy_explanation">Det här innehållet kan användas efter inloggning på PlayStation®Network och kopiering av innehållet till det här systemets hårddisk.
Du kan även spela innehållet på ett PSP™-system om du kopierar det till ett sådant.</Text>
	<Text name="msg_error_service_not_available_region">Denna tjänst är inte tillgänglig i ditt land/din region.</Text>
	<Text name="msg_sigining_in2">Loggar in...</Text>
	<Text name="msg_auto_signin_off">Automatisk utloggning</Text>
	<Text name="msg_auto_signin_off_ask">Du måste ange ett lösenord när du loggar in till PlayStation®Network.
Vill du fortsätta?</Text>
	<Text name="msg_signout">Logga ut</Text>
	<Text name="msg_auto_signin">Automatisk inloggning</Text>
	<Text name="msg_error_no_execute_psn_maintenance_partially">Åtgärden kan inte utföras.
Det utförs för närvarande underhåll av PlayStation®Network.</Text>
	<Text name="msg_error_no_player">Inga spelare hittades.</Text>
	<Text name="msg_signin">Logga in</Text>
	<Text name="msg_ignore_list">Lista över blockerade</Text>
	<Text name="msg_friend_register">Lägg till en vän</Text>
	<Text name="msg_play_with">Spelare jag mött</Text>
	<Text name="msg_av_chatroom">Röst-/videochattrum</Text>
	<Text name="msg_game_chatroom">Spelchattrum</Text>
	<Text name="msg_msg_box">Meddelanderuta</Text>
	<Text name="msg_last_signin_minute_ago">Senaste inloggning: för %1 minuter sedan</Text>
	<Text name="msg_last_signin_hour_ago">Senaste inloggning: för %1 timmar sedan</Text>
	<Text name="msg_last_signin_day_ago">Senaste inloggning: för %1 dagar sedan</Text>
	<Text name="msg_last_signin_month_ago">Senaste inloggning: för %1 månader sedan</Text>
	<Text name="msg_last_signin_more_than_2year_ago">Senaste inloggning: för mer än 2 år sedan</Text>
	<Text name="msg_to">Till</Text>
	<Text name="msg_sent">Skickningen har slutförts.</Text>
	<Text name="msg_registered">Tilläggningen har slutförts.</Text>
	<Text name="msg_register_request">Begäran att lägga till en vän</Text>
	<Text name="msg_error_registered_number_over">Det högsta antalet personer som kan läggas till har nåtts.</Text>
	<Text name="msg_error_cannot_register_myself">Du kan inte lägga till dig själv.</Text>
	<Text name="msg_asking_to_add">Väntar på svar för att lägga till som vän.</Text>
	<Text name="msg_asked_to_add">Du har fått en begäran om att lägga till en vän.</Text>
	<Text name="msg_accept_friend_register_ask">Vill du lägga till denna som vän?</Text>
	<Text name="msg_msg_list">Meddelandelista</Text>
	<Text name="msg_start_new_chat">Starta en ny chatt</Text>
	<Text name="msg_new_msg">Skapa meddelande</Text>
	<Text name="msg_error_no_msg">Det finns inte några meddelanden.</Text>
	<Text name="msg_status_f">Status</Text>
	<Text name="msg_name_f">Namn</Text>
	<Text name="msg_reply_to_friend_register">Svara på begäran om att lägga till en vän</Text>
	<Text name="msg_online_id">Online-ID</Text>
	<Text name="msg_online_name">Onlinenamn</Text>
	<Text name="msg_about_me">Om mig</Text>
	<Text name="msg_my_lang">Mina språk</Text>
	<Text name="msg_received_msg_count">Mottagna meddelanden</Text>
	<Text name="msg_unread_msg_count">Olästa meddelanden</Text>
	<Text name="msg_protect_msg_count">Skyddade meddelanden</Text>
	<Text name="msg_sent_msg_count">Skickade meddelanden</Text>
	<Text name="msg_received_msg_count_with_variable">Mottagna meddelanden %1</Text>
	<Text name="msg_sent_msg_count_with_variable">Skickade meddelanden %1</Text>
	<Text name="msg_from">Från</Text>
	<Text name="msg_received_datetime">Mottaget</Text>
	<Text name="msg_sent_datetime">Skickat</Text>
	<Text name="msg_status">Status</Text>
	<Text name="msg_profile">Profil</Text>
	<Text name="msg_online">Online</Text>
	<Text name="msg_afk">Ej tillgänglig</Text>
	<Text name="msg_signing_out">Loggar ut...
Vänta.</Text>
	<Text name="msg_auto_signin_guid">Loggar in automatiskt till PlayStation®Network vid PS3™-systeminloggning.</Text>
	<Text name="msg_del_friend_ask">Den här vännen kommer att raderas.
Om du raderar vännen kommer du att raderas från den personens vänlista.
Vill du fortsätta?</Text>
	<Text name="msg_del_addingfriend_ask">En vän som väntar på att läggas till kommer att raderas.
Om du raderar vännen kommer du att raderas från den personens vänlista.
Vill du fortsätta?</Text>
	<Text name="msg_add_ignore_list">Lägg till i lista över blockerade</Text>
	<Text name="msg_game_title">Speltitel</Text>
	<Text name="msg_information">Information</Text>
	<Text name="msg_played_date_hour">Spelat</Text>
	<Text name="msg_add_ignore_list_ask">Om du lägger till någon i listan över blockerade kan du inte längre ta emot meddelanden från denna person.
Vill du fortsätta?</Text>
	<Text name="msg_adding">Lägger till...
Vänta.</Text>
	<Text name="msg_del_from_ignore_list">Radera från lista över blockerade</Text>
	<Text name="msg_del_ignore_list_ask">Vill du radera från listan över blockerade?</Text>
	<Text name="msg_error_not_registered">Inga personer har lagts till.</Text>
	<Text name="msg_error_try_again_later">Ett fel har inträffat.
Försök igen senare.</Text>
	<Text name="msg_send_grief_report">Anmäl innehåll</Text>
	<Text name="msg_received_box">Mottaget</Text>
	<Text name="msg_sent_box">Skickat</Text>
	<Text name="msg_list">Lista</Text>
	<Text name="msg_protect">Skydda</Text>
	<Text name="msg_unprotected">Ta bort skydd</Text>
	<Text name="msg_edit">Redigera</Text>
	<Text name="msg_attach_image_select">Välj en bild att bifoga.</Text>
	<Text name="msg_attach_cancel_ask">Vill du avbryta bifogningsåtgärden?</Text>
	<Text name="msg_dell_msg_all_ask">Vill du radera alla meddeladen?
Skyddade meddelanden raderas inte.</Text>
	<Text name="msg_del_msgl_ask">Vill du radera meddelandet?</Text>
	<Text name="msg_dell_msg_all_ask2">Vill du radera alla meddelanden?</Text>
	<Text name="msg_voice_text_chatroom">Röst-/textchattrum</Text>
	<Text name="msg_text_chatroom">Chattrum (endast text)</Text>
	<Text name="msg_mic_on">Mikrofon på</Text>
	<Text name="msg_mic_off">Mikrofon av</Text>
	<Text name="msg_chat_volume">Chattvolym</Text>
	<Text name="msg_camera_on">Kamera på</Text>
	<Text name="msg_camera_off">Kamera av</Text>
	<Text name="msg_chat_screen_on">Visa chattbild</Text>
	<Text name="msg_chat_screen_off">Dölj chattbild</Text>
	<Text name="msg_invite_friend">Bjud in en vän</Text>
	<Text name="msg_new_msg_all">Skapa meddelande till alla</Text>
	<Text name="msg_quit">Lämna</Text>
	<Text name="msg_cancel2">Avsluta</Text>
	<Text name="msg_invite_chat">Chattinbjudan</Text>
	<Text name="msg_participants_list">Deltagarlista</Text>
	<Text name="msg_invite_game">Spelinbjudan</Text>
	<Text name="msg_error_add">Ett fel uppstod under tilläggsåtgärden.</Text>
	<Text name="msg_error_attach_size_over">Det högsta antalet filer som kan bifogas har uppnåtts.</Text>
	<Text name="msg_error_attach_deleted">Den bifogade filen har raderats.</Text>
	<Text name="msg_error_player_added">Den här spelaren har redan lagts till.</Text>
	<Text name="msg_protect_msg_over">Det högsta tillåtna antalet meddelanden som kan skyddas har uppnåtts.
Du kan skydda upp till 50 meddelanden.</Text>
	<Text name="msg_error_cannot_operate_signin_pls">Åtgärden kan inte utföras.
Du är inte inloggad.</Text>
	<Text name="msg_error_cannot_operate_remoteplay">Den här åtgärden kan inte utföras under fjärrspel.</Text>
	<Text name="msg_error_cannot_creat_message">Du kan inte skapa något meddelande nu.</Text>
	<Text name="msg_error_ignore_list_friend">Du kan inte lägga till en vän i din lista över blockerade.
Du måste radera personen från din vänlista innan du lägger till honom/henne till din lista över blockerade.</Text>
	<Text name="msg_version">Version</Text>
	<Text name="msg_new_user_create">Skapa ny användare</Text>
	<Text name="msg_logout_ask">Vill du logga ut?</Text>
	<Text name="msg_login_ask">Vill du logga in som den valda användaren?
Den inloggade användaren loggas ut.</Text>
	<Text name="msg_username_create">Ange ett användarnamn.</Text>
	<Text name="msg_error_max_num_users_reached">Det går inte att skapa fler användare.
Det går att skapa högst 16 användare.</Text>
	<Text name="msg_error_other_username_create_pls">Det angivna namnet används redan.
Ange ett annat användarnamn.</Text>
	<Text name="msg_error_new_user_create">Ett fel inträffade när användaren skapades.</Text>
	<Text name="msg_user_del_2nd_ask">Ska användaren raderas?</Text>
	<Text name="msg_auto_login_set">Från och med nu loggas "%1" in automatiskt när du startar PS3™-systemet.</Text>
	<Text name="msg_username">Användare</Text>
	<Text name="msg_username_num">Användare %1</Text>
	<Text name="msg_auto_login">Automatisk inloggning</Text>
	<Text name="msg_logout">Logga ut</Text>
	<Text name="msg_user_del_ask">Om du raderar användaren, raderas också sparade data för PlayStation®3-programvaran, meddelanden, trophies och annan information.
Vill du fortsätta?</Text>
	<Text name="msg_error_character">Det går inte att ange följande tecken:
%1</Text>
	<Text name="msg_tool_rebug_file"><![CDATA[★ Rebug Essentials]]></Text>
	<Text name="msg_tool_rebug_file_info">INSTALL essential tools to fully enjoy the REBUG experience.</Text>
	<Text name="msg_tool_psn_file"><![CDATA[★ PlayStation®Network Content]]></Text>
	<Text name="msg_tool_psn_file_info">Manage your downloaded PlayStation®Network Content.</Text>
	<Text name="msg_tool_install_file"><![CDATA[★ Install Package Files]]></Text>
	<Text name="msg_tool_install_file_info">INSTALL package files from Storage Devices and your PS3™.</Text>
	<Text name="msg_tool_delete_file"><![CDATA[★ Delete Package Files]]></Text>
	<Text name="msg_tool_delete_file_info">DELETE package files from Storage Devices and your PS3™.</Text>
	<Text name="msg_tool_hdd0_file">PS3™ Hard Disk</Text>
	<Text name="msg_tool_hdd0_install_info">INSTALL from [dev_hdd0/packages] folder on your PS3™.</Text>
	<Text name="msg_tool_hdd0_delete_info">DELETE from [dev_hdd0/packages] folder on your PS3™.</Text>
	<Text name="msg_tool_usb_file">Package Folder</Text>
	<Text name="msg_tool_usb_install_info">INSTALL from [packages] folder on your Storage Device.</Text>
	<Text name="msg_tool_usb_delete_info">DELETE from [packages] folder on your Storage Device.</Text>
	<Text name="msg_tool_og_file">Standard Package Location</Text>
	<Text name="msg_tool_og_install_info"><![CDATA[INSTALL from the standard [★ Install Package Files] locations.]]></Text>
	<Text name="msg_tool_og_delete_info"><![CDATA[DELETE from the standard [★ Install Package Files] locations.]]></Text>
	<Text name="msg_tool_no_package">No package files found.</Text>
	<Text name="msg_tool_no_psn_content">No PlayStation®Network Content found.</Text>
	<Text name="msg_applications_vita">Applications (PS Vita)</Text>
	<Text name="msg_when_use_content_on_vita_hint">If using the content on a PS Vita system, connect the PS Vita system using a USB cable, and then start [Content Manager] on the PS Vita system.</Text>
	<Text name="msg_remoteplay_explanation"><![CDATA[Use a device that supports remote play (such as a PS Vita or a PSP™ system) to operate this system over a network. Go to [Settings] > [Remote Play Settings] > [Register Device] and register the remote play device.]]></Text>
</TextLang>
