<?xml version="1.0" encoding="UTF-8"?>
<!-- This file was generated by XMB Manager Plus vXMBMP-VERSION Builder Toolkit -->
<XMBML version="1.0">

	<!-- Main (HDD) -->
	<View id="seg_xmb_app">
		<Attributes>
			<Table key="xmb_app">
				<Pair key="icon"><String>/dev_hdd0/game/APPTITLID/USRDIR/IMAGES/xmbmp.png</String></Pair>
				<Pair key="title"><String>LANG_TITL_MAIN</String></Pair>
				<Pair key="info"><String>LANG_INFO_MAIN</String></Pair>
				<Pair key="child"><String>segment</String></Pair>
				<Pair key="ingame"><String>disable</String></Pair>
			</Table>
		</Attributes>
		<Items>
			<Query class="type:x-xmb/folder-pixmap" key="xmb_app" attr="xmb_app" src="#seg_xmb_app_items"/>
		</Items>
	</View>
	<View id="seg_xmb_app_items">
		<Items>
			<Query class="type:x-xmb/folder-pixmap" key="file01" src="xmb://localhost/dev_hdd0/game/APPTITLID/USRDIR/FEATURES/Personal_Area.xml#seg_personalarea"/>
			<Query class="type:x-xmb/folder-pixmap" key="file00" src="xmb://localhost/dev_hdd0/game/APPTITLID/USRDIR/FEATURES/Package_Manager.xml#seg_packagemanager"/>
			<Query class="type:x-xmb/folder-pixmap" key="file05" src="xmb://localhost/dev_hdd0/game/APPTITLID/USRDIR/FEATURES/Download_Manager.xml#seg_downloadmanager"/>
			<Query class="type:x-xmb/folder-pixmap" key="file10" src="xmb://localhost/dev_hdd0/game/APPTITLID/USRDIR/FEATURES/File_Manager.xml#seg_filemanager"/>
			<Query class="type:x-xmb/folder-pixmap" key="file20" src="xmb://localhost/dev_hdd0/game/APPTITLID/USRDIR/FEATURES/Multimedia_Manager.xml#seg_multimediamanager"/> 
			<Query class="type:x-xmb/folder-pixmap" key="file30" src="xmb://localhost/dev_hdd0/game/APPTITLID/USRDIR/FEATURES/Game_Manager.xml#seg_gamemanager"/>
			<Query class="type:x-xmb/folder-pixmap" key="file40" src="xmb://localhost/dev_hdd0/game/APPTITLID/USRDIR/FEATURES/Game_Data_Manager.xml#seg_gamedatamanager"/>
			<Query class="type:x-xmb/folder-pixmap" key="file50" src="xmb://localhost/dev_hdd0/game/APPTITLID/USRDIR/FEATURES/Links.xml#seg_links"/>
			<Query class="type:x-xmb/folder-pixmap" key="file60" src="xmb://localhost/dev_hdd0/game/APPTITLID/USRDIR/game_settings.xml#seg_settings"/>
		</Items>
	</View>

</XMBML>
